gpseer/__init__.py
gpseer/__version__.py
gpseer/cross_validate.py
gpseer/fetch_example.py
gpseer/main.py
gpseer/maximum_likelihood.py
gpseer/plot.py
gpseer/utils.py
gpseer-0.2.dist-info/METADATA
gpseer-0.2.dist-info/WHEEL
gpseer-0.2.dist-info/entry_points.txt
gpseer-0.2.dist-info/top_level.txt
gpseer-0.2.dist-info/RECORD
