Metadata-Version: 2.1
Name: gpseer
Version: 0.2
Summary: Python API to infer missing data in sparsely sampled genotype-phenotype maps.
Home-page: https://github.com/harmslab/gpseer
Author: Zach Sailer
Author-email: zachsailer@gmail.com
License: MIT
Platform: UNKNOWN
Classifier: License :: OSI Approved :: MIT License
Classifier: Programming Language :: Python
Classifier: Programming Language :: Python :: 3.3
Classifier: Programming Language :: Python :: 3.4
Classifier: Programming Language :: Python :: 3.5
Classifier: Programming Language :: Python :: 3.6
Classifier: Programming Language :: Python :: Implementation :: CPython
Classifier: Programming Language :: Python :: Implementation :: PyPy
Requires-Dist: requests
Requires-Dist: numpy
Requires-Dist: pandas
Requires-Dist: gpmap
Requires-Dist: epistasis
Requires-Dist: tqdm
Requires-Dist: matplotlib
Provides-Extra: test
Requires-Dist: pytest ; extra == 'test'
Requires-Dist: pytest-cov ; extra == 'test'
Requires-Dist: pytest-console-scripts ; extra == 'test'
Requires-Dist: pytest-datafiles ; extra == 'test'
